web_operator/__init__.py
web_operator/supervisor.py
web_operator/utils.py
web_operator/nodes/__init__.py
web_operator/nodes/api_operation_node.py
web_operator/nodes/computer_use_node.py
web_operator/nodes/router_node.py
web_operator/nodes/tools.py
web_operator-0.2.1.dist-info/METADATA
web_operator-0.2.1.dist-info/WHEEL
web_operator-0.2.1.dist-info/top_level.txt
web_operator-0.2.1.dist-info/RECORD
