Metadata-Version: 2.2
Name: web_operator
Version: 0.2.1
Summary: A library for automating web tasks
Author: Dhanoop Karunakaran
Project-URL: Homepage, https://github.com/dkarunakaran/web-operator
Project-URL: Bug Tracker, https://github.com/dkarunakaran/web-operator
Classifier: Programming Language :: Python :: 3
Classifier: License :: OSI Approved :: Apache Software License
Classifier: Operating System :: OS Independent
Requires-Python: >=3.11
Requires-Dist: networkx==3.1
Requires-Dist: accelerate==1.3.0
Requires-Dist: qwen-vl-utils==0.0.10
Requires-Dist: flash-attn==2.6.1
Requires-Dist: openai==1.60.2
Requires-Dist: qwen_agent==0.0.15
Requires-Dist: python-dateutil==2.9.0.post0
Requires-Dist: pyautogui==0.9.54
Requires-Dist: python-dotenv==1.0.1
Provides-Extra: test
Requires-Dist: pytest; extra == "test"
